<?xml version="1.0" encoding="UTF-8"?>
<root>
	<common_para_list>
		<common_para>			
			<first_col_width>25%</first_col_width>
			<js_file_name>js_functions_06.js</js_file_name>
			<js_function>set_input()</js_function>
			<list_tag_giay_bien_nhan>ghi_chu,tai_lieu_kt,ho_ten_nk,dia_chi_dk,dien_thoai_nk</list_tag_giay_bien_nhan>
		</common_para>
		<form_title>GIẤY CHỨNG NHẬN ĐĂNG KÝ KINH DOANH HỘ CÁ THỂ</form_title>
	</common_para_list>
	<update_object>
		<table_struct_of_update_form> 
			<update_row_list>	<!--Phan mo ta cac dong Form cap nhat doi tuong-->
				<update_row>
					<have_line_before>false</have_line_before>
					<tag_list>so_dk_kd,ngay_cap_dkkd</tag_list>
					<row_id>so_dk_kd</row_id>
				</update_row>
				<update_row>
					<have_line_before>true</have_line_before>
					<tag_list>hinh_thuc_hs</tag_list>
					<row_id>hinh_thuc_hs</row_id>
				</update_row>
				<update_row>
					<have_line_before>false</have_line_before>
					<tag_list>dk_thay_doi_lan_thu,ngay_dk_thay_doi</tag_list>
					<row_id>dk_thay_doi</row_id>
				</update_row>
				<update_row>
					<have_line_before>false</have_line_before>
					<tag_list>dk_cap_lai_lan_thu,ngay_dk_cap_lai</tag_list>
					<row_id>dk_cap_lai</row_id>
				</update_row>
				<update_row>
					<have_line_before>false</have_line_before>
					<tag_list>gia_tri_den_ngay</tag_list>
					<row_id>gia_tri_den_ngay</row_id>
				</update_row>							
				<update_row>
					<have_line_before>false</have_line_before>
					<tag_list>registor_name,ngay_sinh_nk</tag_list>
					<row_id>registor_name</row_id>
				</update_row>
				<update_row>
					<have_line_before>false</have_line_before>
					<tag_list>gioi_tinh_nk,dan_toc_nk,quoc_tich</tag_list>
					<row_id>dantoc_nk</row_id>
				</update_row>				
				<update_row>
					<have_line_before>false</have_line_before>
					<tag_list>so_cmnd_nk,ngay_cap_socmnd_nk</tag_list>
					<row_id>id_ngaycap_noicap_nk</row_id>
				</update_row>	
				<update_row>
					<have_line_before>false</have_line_before>
					<tag_list>noi_cap_socmnd_nk</tag_list>
					<row_id>noi_cap_socmnd_nk</row_id>
				</update_row>	
				<update_row>
					<have_line_before>false</have_line_before>
					<tag_list>gctcn_nk</tag_list>
					<row_id>id_gctcn_nk</row_id>
				</update_row>	
				<update_row>
					<have_line_before>false</have_line_before>
					<tag_list>so_gct_nk,ngay_cap_sogct_nk</tag_list>
					<row_id>id_ngay_cap_sogct_nk</row_id>
				</update_row>	
				<update_row>
					<have_line_before>false</have_line_before>
					<tag_list>noi_cap_gct_nk</tag_list>
					<row_id>noi_cap_gct_nk</row_id>
				</update_row>
				<update_row>
					<have_line_before>false</have_line_before>
					<tag_list>registor_address</tag_list>
					<row_id>id_registor_address</row_id>
				</update_row>	
				<update_row>
					<have_line_before>false</have_line_before>
					<tag_list>cho_o_hien_tai_nk</tag_list>
					<row_id>id_cho_o_hien_tai_nk</row_id>
				</update_row>	
					
				<update_row>
					<have_line_before>false</have_line_before>
					<tag_list>dien_thoai_nk,so_fax_nk</tag_list>
					<row_id>id_dienthoai_fax_nk</row_id>
				</update_row>
				<update_row>
					<have_line_before>false</have_line_before>
					<tag_list>email_nk,website_nk</tag_list>
					<row_id>id_email_website_nk</row_id>
				</update_row>	
				<!--Het thong tin nguoi khai-->		
				
				<!--Bat dau thong tin nguoi dung ten trong giay chung nhan-->							
				<update_row>
					<have_line_before>true</have_line_before>
					<first_col_width>90%</first_col_width>
					<tag_list>label_noi_dung_dkkd</tag_list>
					<row_id>id_label_noi_dung_dkkd</row_id>
				</update_row>	
				<update_row>
					<have_line_before>false</have_line_before>
					<first_col_width>25%</first_col_width>
					<tag_list>ten_dk</tag_list>
					<row_id>ten_dk</row_id>
				</update_row>			
				
				<update_row>
					<have_line_before>false</have_line_before>
					<tag_list>dia_chi_dk</tag_list>
					<row_id>dia_chi_dk</row_id>
				</update_row>
				
				<update_row>
					<have_line_before>false</have_line_before>
					<tag_list>thuoc_xa_tt</tag_list>
					<row_id>thuoc_xa_tt</row_id>
				</update_row>		
				<update_row>
					<have_line_before>false</have_line_before>
					<tag_list>so_dt_dk,so_fax_dk</tag_list>
					<row_id>id_place_phone</row_id>
				</update_row>					
		
				<update_row>
					<have_line_before>false</have_line_before>
					<tag_list>email_dk,website_dk</tag_list>
					<row_id>id_email_website_registor</row_id>
				</update_row>		
				
				<update_row>
					<have_line_before>false</have_line_before>
					<tag_list>nghe_kd</tag_list>
					<row_id>nghe_kd</row_id>
				</update_row>		
				
				<update_row>
					<have_line_before>false</have_line_before>
					<tag_list>von_kd</tag_list>
					<row_id>von_kd</row_id>
				</update_row>
				<update_row>
					<have_line_before>false</have_line_before>
					<tag_list>von_kd_bang_chu</tag_list>
					<row_id>von_kd_bang_chu</row_id>
				</update_row>		
				<update_row>
					<have_line_before>false</have_line_before>
					<tag_list>ghi_chu</tag_list>
					<row_id>ghi_chu</row_id>
				</update_row>						
			</update_row_list>
		</table_struct_of_update_form>
		<update_formfield_list>	
			<hinh_thuc_hs>
				<label>Hình thức hồ sơ</label>
				<type>selectbox</type>
				<selectbox_option_sql>EfyLib_ListGetAllbyListtypeCode '#OWNER_CODE#', 'DM_HT_DKKD'</selectbox_option_sql>
				<selectbox_option_id_column>0</selectbox_option_id_column>
				<selectbox_option_name_column>1</selectbox_option_name_column>
				<selectbox_option_value_column>1</selectbox_option_value_column>

				<width>65%</width>
				<optional>false</optional>

				<message>Phai xac dinh HINH THUC HO SO</message>

				<xml_data>true</xml_data>

				<js_action_list>onChange</js_action_list>
				<xml_tag_in_db>hinh_thuc_hs</xml_tag_in_db>
				<readonly_in_edit_mode>false</readonly_in_edit_mode>
				<disabled_in_edit_mode>false</disabled_in_edit_mode>
			</hinh_thuc_hs>
			<so_dk_kd>
				<label>Số ĐKKD</label>
				<type>textbox</type>
				<data_format>text</data_format>
				<width>40%</width>
				<optional>false</optional>
				<max_length>50</max_length>
				<message>Phai xac dinh SO DANG KY KINH DOANH</message>

				<xml_data>true</xml_data>


				<xml_tag_in_db>so_dk_kd</xml_tag_in_db>
				<readonly_in_edit_mode>false</readonly_in_edit_mode>
				<disabled_in_edit_mode>false</disabled_in_edit_mode>
			</so_dk_kd>
			<dk_thay_doi_lan_thu>
				<label>Đăng ký thay đổi lần thứ</label>
				<type>textbox</type>
				<data_format>isnumeric</data_format>
				<width>35%</width>
				<optional>true</optional>
				<max_length>50</max_length>
				<message>So lan thay daoi phai la so nguyen</message>

				<xml_data>true</xml_data>


				<xml_tag_in_db>dk_thay_doi_lan_thu</xml_tag_in_db>
				<readonly_in_edit_mode>false</readonly_in_edit_mode>
				<disabled_in_edit_mode>false</disabled_in_edit_mode>
			</dk_thay_doi_lan_thu>
			<ngay_dk_thay_doi>
				<label>Ngày đăng ký thay đổi</label>
				<width_label>15%;text-align:left;padding-left:5px;</width_label>
				<type>textbox</type>
				<data_format>isdate</data_format>
				<width>14.3%</width>
				<optional>true</optional>





				<xml_data>true</xml_data>


				<xml_tag_in_db>ngay_dk_thay_doi</xml_tag_in_db>
				<readonly_in_edit_mode>false</readonly_in_edit_mode>
				<disabled_in_edit_mode>false</disabled_in_edit_mode>
			</ngay_dk_thay_doi>
			<dk_cap_lai_lan_thu>
				<label>Đăng ký thay đổi lần thứ</label>
				<type>textbox</type>
				<data_format>isnumeric</data_format>
				<width>35%</width>
				<optional>true</optional>
				<max_length>50</max_length>
				<message>Lan cap lai phai la so nguyen</message>

				<xml_data>true</xml_data>


				<xml_tag_in_db>dk_cap_lai_lan_thu</xml_tag_in_db>
				<disabled_in_edit_mode>false</disabled_in_edit_mode>
			</dk_cap_lai_lan_thu>
			<ngay_dk_cap_lai>
				<label>Ngày đăng ký cấp lại</label>
				<width_label>15%;text-align:left;padding-left:5px;</width_label>
				<type>textbox</type>
				<data_format>isdate</data_format>
				<width>14.3%</width>
				<optional>true</optional>





				<xml_data>true</xml_data>


				<xml_tag_in_db>ngay_dk_cap_lai</xml_tag_in_db>
				<readonly_in_edit_mode>false</readonly_in_edit_mode>
				<disabled_in_edit_mode>false</disabled_in_edit_mode>
			</ngay_dk_cap_lai>
			<gia_tri_den_ngay>
				<label>Có giá trị đến ngày</label>
				<width_label></width_label>
				<type>textbox</type>
				<data_format>isdate</data_format>
				<width>20%</width>
				<optional>true</optional>





				<xml_data>true</xml_data>


				<xml_tag_in_db>gia_tri_den_ngay</xml_tag_in_db>
				<readonly_in_edit_mode>false</readonly_in_edit_mode>
				<disabled_in_edit_mode>false</disabled_in_edit_mode>
			</gia_tri_den_ngay>
			<ngay_cap_dkkd>
				<label>Ngày ban hành</label>
				<width_label>10%;text-align:left;padding-left:5px;</width_label>
				<type>textbox</type>
				<data_format>isdate</data_format>
				<width>14.3%</width>
				<optional>false</optional>





				<xml_data>true</xml_data>


				<xml_tag_in_db>ngay_cap_dkkd</xml_tag_in_db>
				<readonly_in_edit_mode>false</readonly_in_edit_mode>
				<disabled_in_edit_mode>false</disabled_in_edit_mode>
			</ngay_cap_dkkd>
			<hs_lan_thu>
				<label>Lần thứ</label>
				<width_label>10%;text-align:left;padding-left:5px;</width_label>
				<type>textbox</type>
				<data_format>text</data_format>
				<optional>true</optional>
				<width>14.3%</width>
				<max_length>100</max_length>
				<message>Phai xac dinh LAN THU bao nhieu</message>

				<xml_data>true</xml_data>


				<xml_tag_in_db>hs_lan_thu</xml_tag_in_db>
				<readonly_in_edit_mode>false</readonly_in_edit_mode>
				<disabled_in_edit_mode>false</disabled_in_edit_mode>
			</hs_lan_thu>
	<!--Thong tin nguoi di khai!-->
			<registor_name>
				<label>Họ tên cá nhân/ Tổ chức  </label>
				<type>textbox</type>
				<data_format>text</data_format>
				<optional>false</optional>
				<width>40%</width>
				<max_length>100</max_length>
				<message>Phai xac dinh HO TEN nguoi dang ky</message>

				<xml_data>true</xml_data>
				<js_function_list>set_upcase_value(this)</js_function_list>
				<js_action_list>onChange</js_action_list>
				<xml_tag_in_db>registor_name</xml_tag_in_db>
				<readonly_in_edit_mode>false</readonly_in_edit_mode>
				<disabled_in_edit_mode>false</disabled_in_edit_mode>
			</registor_name>
			<gioi_tinh_nk>
				<label>Giới tính</label>
				<type>selectbox</type>
				<selectbox_option_sql>EfyLib_ListGetAllbyListtypeCode '#OWNER_CODE#', 'DM_GT'</selectbox_option_sql>
				<selectbox_option_id_column>0</selectbox_option_id_column>
				<selectbox_option_name_column>1</selectbox_option_name_column>
				<selectbox_option_value_column>1</selectbox_option_value_column>

				<width>15%</width>
				<optional>true</optional>

				<message>Phai xac dinh GIOI TINH</message>

				<xml_data>true</xml_data>


				<xml_tag_in_db>gioi_tinh_nk</xml_tag_in_db>
				<readonly_in_edit_mode>false</readonly_in_edit_mode>
				<disabled_in_edit_mode>false</disabled_in_edit_mode>
			</gioi_tinh_nk>
			
			<ngay_sinh_nk>
				<label>Ngày sinh</label>
				<width_label>10%;text-align:left;padding-left:5px;</width_label>
				<type>textbox</type>
				<data_format>isdate</data_format>
				<width>14.3%</width>
				<optional>true</optional>





				<xml_data>true</xml_data>


				<xml_tag_in_db>ngay_sinh_nk</xml_tag_in_db>
				<readonly_in_edit_mode>false</readonly_in_edit_mode>
				<disabled_in_edit_mode>false</disabled_in_edit_mode>
			</ngay_sinh_nk>
			
			<dan_toc_nk>
				<label>Dân tộc</label>
				<width_label>10%;text-align:left;padding-left:5px;</width_label>
				<type>textbox</type>
				<data_format>text</data_format>
				<optional>true</optional>
				<width>14.5%</width>
				<max_length>100</max_length>
				<message>Phai xac dinh DAN TOC nguoi dang ky</message>

				<xml_data>true</xml_data>
				<default_value>Kinh</default_value>


				<xml_tag_in_db>dan_toc_nk</xml_tag_in_db>
				<readonly_in_edit_mode>false</readonly_in_edit_mode>
				<disabled_in_edit_mode>false</disabled_in_edit_mode>
			</dan_toc_nk>
			<quoc_tich>
				<label>Quốc tịch</label>
				<width_label>10%;text-align:left;padding-left:5px;</width_label>
				<type>textbox</type>
				<data_format>text</data_format>
				<optional>true</optional>
				<width>14.3%</width>
				<max_length>100</max_length>
				<message>Phai xac dinh QUOC TICH nguoi dang ky</message>

				<xml_data>true</xml_data>
				<default_value>Việt Nam</default_value>


				<xml_tag_in_db>quoc_tich</xml_tag_in_db>
				<readonly_in_edit_mode>false</readonly_in_edit_mode>
				<disabled_in_edit_mode>false</disabled_in_edit_mode>
			</quoc_tich>
	
			<so_cmnd_nk>
				<label>Số CMND</label>
				<type>textbox</type>
				<data_format>text</data_format>
				<optional>true</optional>
				<width>40%</width>
				<max_length>12</max_length>
				<message>SO CMND khong duoc de trong!</message>

				<xml_data>true</xml_data>



				<xml_tag_in_db>so_cmnd_nk</xml_tag_in_db>
				<readonly_in_edit_mode>false</readonly_in_edit_mode>
				<disabled_in_edit_mode>false</disabled_in_edit_mode>
			</so_cmnd_nk>	
			<ngay_cap_socmnd_nk>
				<label>Ngày cấp</label>
				<width_label>10%;text-align:left;padding-left:5px;</width_label>
				<type>textbox</type>
				<data_format>isdate</data_format>
				<width>14.3%</width>
				<optional>true</optional>





				<xml_data>true</xml_data>


				<xml_tag_in_db>ngay_cap_socmnd_nk</xml_tag_in_db>
				<readonly_in_edit_mode>false</readonly_in_edit_mode>
				<disabled_in_edit_mode>false</disabled_in_edit_mode>
			</ngay_cap_socmnd_nk>	
			<noi_cap_socmnd_nk>
				<label>Nơi cấp</label>
				<type>textbox</type>
				<data_format>text</data_format>
				<optional>true</optional>
				<width>65%</width>
				<max_length>100</max_length>
				<message>NOI CAP khong duoc de trang!</message>

				<xml_data>true</xml_data>



				<xml_tag_in_db>noi_cap_socmnd_nk</xml_tag_in_db>
				<readonly_in_edit_mode>false</readonly_in_edit_mode>
				<disabled_in_edit_mode>false</disabled_in_edit_mode>
			</noi_cap_socmnd_nk>	
			<gctcn_nk>
				<label>Giấy tờ chứng thực cá nhân khác (nếu không có CMND)</label>
				<type>textbox</type>
				<data_format>text</data_format>
				<optional>true</optional>
				<width>65%</width>
				<max_length>12</max_length>


				<xml_data>true</xml_data>



				<xml_tag_in_db>gctcn_nk</xml_tag_in_db>
				<readonly_in_edit_mode>false</readonly_in_edit_mode>
				<disabled_in_edit_mode>false</disabled_in_edit_mode>
			</gctcn_nk>	
			<so_gct_nk>
				<label>Số giấy chứng thực cá nhân</label>
				<type>textbox</type>
				<data_format>text</data_format>
				<optional>true</optional>
				<width>40%</width>
				<max_length>12</max_length>


				<xml_data>true</xml_data>



				<xml_tag_in_db>so_gct_nk</xml_tag_in_db>
				<readonly_in_edit_mode>false</readonly_in_edit_mode>
				<disabled_in_edit_mode>false</disabled_in_edit_mode>
			</so_gct_nk>	
			<ngay_cap_sogct_nk>
				<label>Ngày cấp</label>
				<width_label>10%;text-align:left;padding-left:5px;</width_label>
				<type>textbox</type>
				<data_format>isdate</data_format>
				<width>14.3%</width>
				<optional>true</optional>





				<xml_data>true</xml_data>


				<xml_tag_in_db>ngay_cap_sogct_nk</xml_tag_in_db>
				<readonly_in_edit_mode>false</readonly_in_edit_mode>
				<disabled_in_edit_mode>false</disabled_in_edit_mode>
			</ngay_cap_sogct_nk>	
			<noi_cap_gct_nk>
				<label>Nơi cấp</label>
				<type>textbox</type>
				<data_format>text</data_format>
				<optional>true</optional>
				<width>65%</width>
				<max_length>100</max_length>
				<message>NOI CAP khong duoc de trang!</message>

				<xml_data>true</xml_data>



				<xml_tag_in_db>noi_cap_gct_nk</xml_tag_in_db>
				<readonly_in_edit_mode>false</readonly_in_edit_mode>
				<disabled_in_edit_mode>false</disabled_in_edit_mode>
			</noi_cap_gct_nk>	
	
			<registor_address>
				<label>Nơi đăng ký hộ khẩu thường trú:</label>
				<type>textbox</type>
				<data_format>text</data_format>
				<optional>false</optional>
				<width>65%</width>

				<message>Phai xach dinh NOI DANG KY HO KHAU THUONG TRU !</message>

				<xml_data>true</xml_data>



				<xml_tag_in_db>registor_address</xml_tag_in_db>
				<readonly_in_edit_mode>false</readonly_in_edit_mode>
				<disabled_in_edit_mode>false</disabled_in_edit_mode>
			</registor_address>	
	
			<cho_o_hien_tai_nk>
				<label>Chỗ ở hiện tại</label>
				<type>textbox</type>
				<data_format>text</data_format>
				<optional>true</optional>
				<width>65%</width>

				<message>CHO O HIEN TAI khong duoc de trang!</message>

				<xml_data>true</xml_data>



				<xml_tag_in_db>cho_o_hien_tai_nk</xml_tag_in_db>
				<readonly_in_edit_mode>false</readonly_in_edit_mode>
				<disabled_in_edit_mode>false</disabled_in_edit_mode>
			</cho_o_hien_tai_nk>	
	
			<dien_thoai_nk>
				<label>Điện thoại</label>
				<type>textbox</type>
				<data_format>text</data_format>
				<optional>true</optional>
				<width>30%</width>
				<max_length>100</max_length>
				<message>DIEN THOAI khong dung dinh dang!</message>

				<xml_data>true</xml_data>



				<xml_tag_in_db>dien_thoai_nk</xml_tag_in_db>
				<readonly_in_edit_mode>false</readonly_in_edit_mode>
				<disabled_in_edit_mode>false</disabled_in_edit_mode>
			</dien_thoai_nk>
	
			<so_fax_nk>
				<label>Fax</label>
				<width_label>10%;text-align:left;padding-left:5px;</width_label>
				<type>textbox</type>
				<data_format>text</data_format>
				<optional>true</optional>
				<width>24.3%</width>

				<message>SO FAX khong dung dinh dang!</message>

				<xml_data>true</xml_data>



				<xml_tag_in_db>so_fax_nk</xml_tag_in_db>
				<readonly_in_edit_mode>false</readonly_in_edit_mode>
				<disabled_in_edit_mode>false</disabled_in_edit_mode>
			</so_fax_nk>
	
			<email_nk>
				<label>Địa chỉ e-mail</label>
				<type>textbox</type>
				<data_format>isemail</data_format>
				<width>30%</width>
				<optional>true</optional>
				<max_length>200</max_length>
				<message>Dia chi EMAIL khong hop le!</message>

				<xml_data>true</xml_data>
				<tooltip>Địa chỉ E-mail phải nhập theo định dạng tên_người_dụng@tên_máy_chủ_email (ví dụ:tennguoidung@yahoo.com)</tooltip>


				<xml_tag_in_db>email_nk</xml_tag_in_db>
				<readonly_in_edit_mode>false</readonly_in_edit_mode>
				<disabled_in_edit_mode>false</disabled_in_edit_mode>
			</email_nk>
	
			<website_nk>
				<label>Website</label>
				<width_label>10%;text-align:left;padding-left:5px;</width_label>
				<type>textbox</type>
				<data_format>text</data_format>
				<optional>true</optional>
				<width>24.3%</width>

				<message>WEBSITE khong hop le!</message>

				<xml_data>true</xml_data>



				<xml_tag_in_db>website_nk</xml_tag_in_db>
				<readonly_in_edit_mode>false</readonly_in_edit_mode>
				<disabled_in_edit_mode>false</disabled_in_edit_mode>
			</website_nk>
			<!--Het thong tin nguoi khai-->
			
			<label_noi_dung_dkkd>
				<label>&lt;center&gt; &lt;B&gt;ĐĂNG KÝ KINH DOANH HỘ CÁ THỂ VỚI NỘI DUNG SAU&lt;/B&gt; &lt;/left&gt;</label>			
				<type>label</type>
			</label_noi_dung_dkkd>		
			
			<ten_dk>
				<label>Tên hộ kinh doanh</label>
				<type>textbox</type>
				<data_format>text</data_format>
				<width>65%</width>
				<optional>false</optional>
				<max_length>200</max_length>
				<message>Phai xach dinh TEN HO KINH DOANH!</message>

				<xml_data>true</xml_data>
				<js_function_list>set_upcase_value(this)</js_function_list>
				<js_action_list>onChange</js_action_list>
				<xml_tag_in_db>ten_dk</xml_tag_in_db>
				<readonly_in_edit_mode>false</readonly_in_edit_mode>
				<disabled_in_edit_mode>false</disabled_in_edit_mode>
			</ten_dk>	
			
			<dia_chi_dk>
				<label>Địa điểm kinh doanh</label>
				<type>textbox</type>
				<data_format>text</data_format>
				<width>65%</width>
				<optional>false</optional>
				<max_length>200</max_length>
				<message>Phai xac dinh DIA DIEM KINH DOANH!</message>

				<xml_data>true</xml_data>

				<js_action_list>onChange</js_action_list>
				<xml_tag_in_db>dia_chi_dk</xml_tag_in_db>
				<readonly_in_edit_mode>false</readonly_in_edit_mode>
				<disabled_in_edit_mode>false</disabled_in_edit_mode>
			</dia_chi_dk>		
			
			<thuoc_xa_tt>
				<label>Thuộc xã</label>
				<type>selectbox</type>
				<selectbox_option_sql>EfyLib_ListGetAllbyListtypeCode '#OWNER_CODE#', 'PHUONG_XA'</selectbox_option_sql>
				<selectbox_option_id_column>0</selectbox_option_id_column>
				<selectbox_option_name_column>1</selectbox_option_name_column>
				<selectbox_option_value_column>1</selectbox_option_value_column>

				<width>30%</width>
				<optional>false</optional>

				<message>Phai xac dinh thong tin PHUONG!</message>

				<xml_data>true</xml_data>
				<tooltip>Dia chi PHUONG</tooltip>


				<xml_tag_in_db>thuoc_xa_tt</xml_tag_in_db>
				<readonly_in_edit_mode>false</readonly_in_edit_mode>
				<disabled_in_edit_mode>false</disabled_in_edit_mode>
			</thuoc_xa_tt>	
				
			<so_dt_dk>
				<label>Điện thoại</label>
				<type>textbox</type>
				<data_format>text</data_format>
				<optional>true</optional>
				<width>30%</width>
				<max_length>100</max_length>
				<message>DIEN THOAI khong dung dinh dang!</message>

				<xml_data>true</xml_data>



				<xml_tag_in_db>so_dt_dk</xml_tag_in_db>
				<readonly_in_edit_mode>false</readonly_in_edit_mode>
				<disabled_in_edit_mode>false</disabled_in_edit_mode>
			</so_dt_dk>
	
			<so_fax_dk>
				<label>Fax</label>
				<width_label>10%;text-align:left;padding-left:5px;</width_label>
				<type>textbox</type>
				<data_format>text</data_format>
				<optional>true</optional>
				<width>24.3%</width>

				<message>SO FAX khong dung dinh dang!</message>

				<xml_data>true</xml_data>



				<xml_tag_in_db>so_fax_dk</xml_tag_in_db>
				<readonly_in_edit_mode>false</readonly_in_edit_mode>
				<disabled_in_edit_mode>false</disabled_in_edit_mode>
			</so_fax_dk>
	
			<email_dk>
				<label>Địa chỉ e-mail</label>
				<type>textbox</type>
				<data_format>isemail</data_format>
				<width>30%</width>
				<optional>true</optional>
				<max_length>200</max_length>
				<message>Dia chi EMAIL khong hop le!</message>

				<xml_data>true</xml_data>
				<tooltip>Địa chỉ E-mail phải nhập theo định dạng tên_người_dụng@tên_máy_chủ_email (ví dụ:tennguoidung@yahoo.com)</tooltip>


				<xml_tag_in_db>email_dk</xml_tag_in_db>
				<readonly_in_edit_mode>false</readonly_in_edit_mode>
				<disabled_in_edit_mode>false</disabled_in_edit_mode>
			</email_dk>
	
			<website_dk>
				<label>Website</label>
				<width_label>10%;text-align:left;padding-left:5px;</width_label>
				<type>textbox</type>
				<data_format>text</data_format>
				<optional>true</optional>
				<width>24.3%</width>

				<message>WEBSITE khong hop le!</message>

				<xml_data>true</xml_data>



				<xml_tag_in_db>website_dk</xml_tag_in_db>
				<readonly_in_edit_mode>false</readonly_in_edit_mode>
				<disabled_in_edit_mode>false</disabled_in_edit_mode>
			</website_dk>
	
			<nghe_kd>
				<label>Ngành nghề kinh doanh</label>
				<type>textarea</type>

				<width>65%</width>
				<row>3</row>
				<optional>false</optional>
				<max_length>200</max_length>
				<message>Phai xac dinh NGANH NGHE KINH DOANH!</message>

				<xml_data>true</xml_data>


				<xml_tag_in_db>nghe_kd</xml_tag_in_db>
				<readonly_in_edit_mode>false</readonly_in_edit_mode>
				<disabled_in_edit_mode>false</disabled_in_edit_mode>
			</nghe_kd>	
			<von_kd>
				<label>Vốn kinh doanh</label>
				<type>textbox</type>
				<data_format>ismoney</data_format>
				<width>30%</width>
				<row>3</row>
				<optional>false</optional>
				<max_length>13</max_length>
				<message>VON KINH DOANH khong hop le</message>
				<note> (đồng)</note>
				<xml_data>true</xml_data>
				<js_function_list>business_capital_onchange(this)</js_function_list>
				<js_action_list>OnBlur()</js_action_list>
				<xml_tag_in_db>von_kd</xml_tag_in_db>
				<readonly_in_edit_mode>false</readonly_in_edit_mode>
				<disabled_in_edit_mode>false</disabled_in_edit_mode>
			</von_kd>
			<von_kd_bang_chu>
				<label>Vốn kinh doanh(bằng chữ)</label>
				<type>textbox</type>
				<data_format>text</data_format>
				<width>65%</width>
				<row>3</row>
				<optional>true</optional>
				<max_length>1000</max_length>
				<message>VON KINH DOANH khong hop le</message>

				<xml_data>true</xml_data>


				<xml_tag_in_db>von_kd_bang_chu</xml_tag_in_db>
				<readonly_in_edit_mode>false</readonly_in_edit_mode>
				<disabled_in_edit_mode>false</disabled_in_edit_mode>
			</von_kd_bang_chu>
			<ghi_chu>
				<label>Ghi chú</label>
				<type>textarea</type>

				<width>65%</width>

				<optional>true</optional>
				<max_length>200</max_length>


				<xml_data>true</xml_data>


				<xml_tag_in_db>ghi_chu</xml_tag_in_db>
				<readonly_in_edit_mode>false</readonly_in_edit_mode>
				<disabled_in_edit_mode>false</disabled_in_edit_mode>
			</ghi_chu>	
		</update_formfield_list>
		<update_sql>Exec EfyLib_ListUpdate #list_id#, #listtype_id#, '#list_code#', '#list_name#', #list_order#, '#list_status#', '#xml_data#', '#deleted_exist_file_id_list#', '#new_file_id_list#','#p_owner_code_list#'</update_sql>
	</update_object>
</root>